LICENSE
MANIFEST.in
README.rst
setup.cfg
setup.py
django_geographical_module.egg-info/PKG-INFO
django_geographical_module.egg-info/SOURCES.txt
django_geographical_module.egg-info/dependency_links.txt
django_geographical_module.egg-info/requires.txt
django_geographical_module.egg-info/top_level.txt
geographical_module/__init__.py
geographical_module/apps.py
geographical_module/tests.py
geographical_module/utils.py
geographical_module/management/__init__.py
geographical_module/management/commands/__init__.py
geographical_module/management/commands/load_geo_records.py
geographical_module/management/commands/load_nuts_postcode_records.py
geographical_module/migrations/0001_initial.py
geographical_module/migrations/0002_alter_geography_unique_together_geography_continent_and_more.py
geographical_module/migrations/0003_add_italian_province_code.py
geographical_module/migrations/__init__.py
geographical_module/models/__init__.py
geographical_module/models/geography.py
geographical_module/scripts/__init__.py
geographical_module/scripts/nuts_postcode.py